pyvectorial_au/__init__.py
pyvectorial_au/aperture/__init__.py
pyvectorial_au/aperture/aperture.py
pyvectorial_au/aperture/uncentered_rectangular_aperture.py
pyvectorial_au/backends/__init__.py
pyvectorial_au/backends/fortran_version.py
pyvectorial_au/backends/python_version.py
pyvectorial_au/backends/rust_version.py
pyvectorial_au/bin/fvm_m1
pyvectorial_au/bin/rust_vect_m1
pyvectorial_au/db/__init.py__
pyvectorial_au/db/cache_init.py
pyvectorial_au/db/cache_io.py
pyvectorial_au/db/vectorial_model_cache.py
pyvectorial_au/encoding/__init__.py
pyvectorial_au/encoding/encoding_and_hashing.py
pyvectorial_au/graphing/__init__.py
pyvectorial_au/graphing/haser_matplotlib.py
pyvectorial_au/graphing/vm_matplotlib.py
pyvectorial_au/graphing/vm_plotly.py
pyvectorial_au/haser/__init__.py
pyvectorial_au/haser/haser_fits.py
pyvectorial_au/haser/haser_params.py
pyvectorial_au/model_input/__init__.py
pyvectorial_au/model_input/vectorial_model_config.py
pyvectorial_au/model_input/vectorial_model_config_reader.py
pyvectorial_au/model_output/__init__.py
pyvectorial_au/model_output/fragment_sputter.py
pyvectorial_au/model_output/vectorial_model_calculation.py
pyvectorial_au/model_output/vectorial_model_result.py
pyvectorial_au/model_running/__init__.py
pyvectorial_au/model_running/vectorial_model_runner.py
pyvectorial_au/post_model_processing/__init__.py
pyvectorial_au/post_model_processing/column_density_abel.py
pyvectorial_au/post_model_processing/fragment_sputter_imaging.py
pyvectorial_au/post_model_processing/fragment_sputter_transform.py
pyvectorial_au/post_model_processing/interpolation.py
pyvectorial_au/pre_model_processing/__init__.py
pyvectorial_au/pre_model_processing/input_transforms.py
pyvectorial_au/pre_model_processing/timedependentproduction.py
pyvectorial_au/tests/__init__.py
pyvectorial_au/tests/input/fort.16
pyvectorial_au/tests/input/rust_out.txt
pyvectorial_au/tests/input/single_run.yaml
pyvectorial_au/tests/input/single_run_binned.yaml
pyvectorial_au-1.1.3.dist-info/METADATA
pyvectorial_au-1.1.3.dist-info/WHEEL
pyvectorial_au-1.1.3.dist-info/entry_points.txt
pyvectorial_au-1.1.3.dist-info/RECORD
